AUTHORS.txt
CHANGELOG.md
LICENSE.txt
MANIFEST.in
README.md
setup.py
Glint.egg-info/PKG-INFO
Glint.egg-info/SOURCES.txt
Glint.egg-info/dependency_links.txt
Glint.egg-info/not-zip-safe
Glint.egg-info/requires.txt
Glint.egg-info/top_level.txt
glint/__init__.py
glint/command.py
glint/runner.py
glint/usage.py
glint/utils.py