Metadata-Version: 1.1
Name: Glint
Version: 0.2.0
Summary: Command line application micro-framework.
Home-page: https://github.com/mlowen/Glint
Author: Mike Lowen
Author-email: mike@mlowen.com
License: MIT
Platform: UNKNOWN
Classifier: Development Status :: 4 - Beta
Classifier: Intended Audience :: Developers
Classifier: Operating System :: OS Independent
Classifier: License :: OSI Approved :: MIT License
Classifier: Environment :: Console
Classifier: Programming Language :: Python :: 3.3
Classifier: Topic :: Software Development :: Libraries :: Application Frameworks
